ankush_hello/__init__.py
ankush_hello/main.py
ankush_hello-1.0.2.dist-info/METADATA
ankush_hello-1.0.2.dist-info/WHEEL
ankush_hello-1.0.2.dist-info/entry_points.txt
ankush_hello-1.0.2.dist-info/top_level.txt
ankush_hello-1.0.2.dist-info/RECORD
